dotdicttools.py
dotdicttools-1.1.0.dist-info/LICENSE
dotdicttools-1.1.0.dist-info/METADATA
dotdicttools-1.1.0.dist-info/WHEEL
dotdicttools-1.1.0.dist-info/top_level.txt
dotdicttools-1.1.0.dist-info/RECORD
