Metadata-Version: 2.1
Name: dotdicttools
Version: 1.1.0
Summary: README.md
Author-email: Patrick Elmer <patrick@elmer.ws>
License: MIT License
Project-URL: Home, https://github.com/dotdict/dotdicttools
Classifier: License :: OSI Approved :: MIT License
License-File: LICENSE
